{"name": "N1_24", "headers": ["terror_property_damage_level", "terror_weaptype_id", "terror_claimmode"], "col_types": ["DString", "DNumber", "DString"], "rows": [{"cells": [{"value": "Minor (likely < $1 million)"}, {"value": 8}, {"value": "Letter"}]}, {"cells": [{"value": "Minor (likely < $1 million)"}, {"value": 8}, {"value": "Letter"}]}, {"cells": [{"value": "Minor (likely < $1 million)"}, {"value": 2}, {"value": "Letter"}]}, {"cells": [{"value": "Minor (likely < $1 million)"}, {"value": 8}, {"value": "Letter"}]}, {"cells": [{"value": "Minor (likely < $1 million)"}, {"value": 6}, {"value": "Letter"}]}, {"cells": [{"value": "Minor (likely < $1 million)"}, {"value": 8}, {"value": "Letter"}]}, {"cells": [{"value": "Minor (likely < $1 million)"}, {"value": 6}, {"value": "Letter"}]}, {"cells": [{"value": "Minor (likely < $1 million)"}, {"value": 6}, {"value": "Letter"}]}, {"cells": [{"value": "Major (likely >= $1 million but < $1 billion)"}, {"value": 8}, {"value": "Unknown"}]}, {"cells": [{"value": "Unknown"}, {"value": 6}, {"value": null}]}, {"cells": [{"value": "Unknown"}, {"value": 8}, {"value": null}]}, {"cells": [{"value": "Unknown"}, {"value": 8}, {"value": "Letter"}]}, {"cells": [{"value": "Unknown"}, {"value": 8}, {"value": "Letter"}]}, {"cells": [{"value": "Unknown"}, {"value": 8}, {"value": "Letter"}]}, {"cells": [{"value": "Major (likely >= $1 million but < $1 billion)"}, {"value": 8}, {"value": null}]}, {"cells": [{"value": "Minor (likely < $1 million)"}, {"value": 8}, {"value": "Unknown"}]}, {"cells": [{"value": "Major (likely >= $1 million but < $1 billion)"}, {"value": 6}, {"value": null}]}, {"cells": [{"value": "Unknown"}, {"value": 8}, {"value": null}]}, {"cells": [{"value": "Unknown"}, {"value": 5}, {"value": null}]}, {"cells": [{"value": "Major (likely >= $1 million but < $1 billion)"}, {"value": 6}, {"value": "Call (pre-incident)"}]}, {"cells": [{"value": "Unknown"}, {"value": 6}, {"value": null}]}, {"cells": [{"value": "Minor (likely < $1 million)"}, {"value": 6}, {"value": "Other"}]}, {"cells": [{"value": "Unknown"}, {"value": 8}, {"value": null}]}, {"cells": [{"value": "Minor (likely < $1 million)"}, {"value": 8}, {"value": "Other"}]}, {"cells": [{"value": "Minor (likely < $1 million)"}, {"value": 8}, {"value": "Other"}]}, {"cells": [{"value": "Minor (likely < $1 million)"}, {"value": 8}, {"value": "Other"}]}, {"cells": [{"value": "Major (likely >= $1 million but < $1 billion)"}, {"value": 8}, {"value": null}]}, {"cells": [{"value": "Major (likely >= $1 million but < $1 billion)"}, {"value": 6}, {"value": null}]}], "base_table_names": ["N1_24", "N1_24", "N1_24"]}